CHANGES.rst
LICENSE
MANIFEST.in
README.rst
pyproject.toml
setup.cfg
setup.py
djangorestframework_security_filters.egg-info/PKG-INFO
djangorestframework_security_filters.egg-info/SOURCES.txt
djangorestframework_security_filters.egg-info/dependency_links.txt
djangorestframework_security_filters.egg-info/requires.txt
djangorestframework_security_filters.egg-info/top_level.txt
rest_framework_permission_filters/__init__.py
rest_framework_permission_filters/mixins.py
rest_framework_permission_filters/permission_filters.py
rest_framework_permission_filters/viewsets.py
rest_framework_role_filters/__init__.py
rest_framework_role_filters/mixins.py
rest_framework_role_filters/role_filters.py
rest_framework_role_filters/viewsets.py