Metadata-Version: 1.1
Name: djangorestframework-security-filters
Version: 0.1.1
Summary: django-rest-framework-security-filters
Home-page: https://gitlab.com/rivercom/django-rest-framework-security-filters
Author: Allisson Azevedo, Sigfrido Pérez
Author-email: allisson@gmail.com, sigfrido.pmp@sigfrido.dev
License: UNKNOWN
Keywords: djangorestframework rest security permission
Platform: UNKNOWN
Classifier: Development Status :: 4 - Beta
Classifier: Environment :: Web Environment
Classifier: Framework :: Django
Classifier: Intended Audience :: Developers
Classifier: License :: OSI Approved :: MIT License
Classifier: Operating System :: OS Independent
Classifier: Programming Language :: Python
Classifier: Programming Language :: Python :: 3
Classifier: Programming Language :: Python :: 3.6
Classifier: Programming Language :: Python :: 3.7
Classifier: Programming Language :: Python :: 3.8
Classifier: Topic :: Internet :: WWW/HTTP
Classifier: Topic :: Software Development :: Libraries :: Application Frameworks
Classifier: Topic :: Software Development :: Libraries :: Python Modules
